dQR/__init__.py
dQR/dqrcode.py
dQR/main.py
dQR-2.0.dist-info/DESCRIPTION.rst
dQR-2.0.dist-info/METADATA
dQR-2.0.dist-info/RECORD
dQR-2.0.dist-info/WHEEL
dQR-2.0.dist-info/entry_points.txt
dQR-2.0.dist-info/metadata.json
dQR-2.0.dist-info/top_level.txt
