Metadata-Version: 2.0
Name: dQR
Version: 2.0
Summary: Translate string in QRcode on terminal.
Home-page: https://github.com/dshowing/dQR
Author: dshowing
Author-email: watt109629@outlook.com
License: Apache-2.0
Platform: UNKNOWN
Classifier: Environment :: Console
Classifier: Intended Audience :: Developers
Classifier: Operating System :: OS Independent
Classifier: Programming Language :: Python :: 2
Classifier: Programming Language :: Python :: 3
Requires-Dist: Pillow (==4.2.1)
Requires-Dist: qrcode (==5.3)
